simple_geocoding/__init__.py
simple_geocoding-0.0.2.dist-info/entry_points.txt
simple_geocoding-0.0.2.dist-info/LICENSE
simple_geocoding-0.0.2.dist-info/WHEEL
simple_geocoding-0.0.2.dist-info/METADATA
simple_geocoding-0.0.2.dist-info/RECORD
