Metadata-Version: 2.1
Name: simple-geocoding
Version: 0.0.2
Summary: Simple geocoding
Home-page: https://github.com/SaitoTsutomu/simple-geocoding
License: MIT
Author: Saito Tsutomu
Author-email: tsutomu7@hotmail.co.jp
Requires-Python: >=3.8,<4.0
Classifier: Development Status :: 1 - Planning
Classifier: License :: OSI Approved :: MIT License
Classifier: Programming Language :: Python
Classifier: Programming Language :: Python :: 3
Classifier: Programming Language :: Python :: 3.8
Classifier: Programming Language :: Python :: 3.9
Classifier: Topic :: Scientific/Engineering
Classifier: Topic :: Software Development
Requires-Dist: fire (>=0.3.1,<0.4.0)
Requires-Dist: pandas (>=1.1.1,<2.0.0)
Requires-Dist: scipy (>=1.5.2,<2.0.0)
